WonderPeaks/.gitignore
WonderPeaks/Helper_Functions.py
WonderPeaks/LICENSE
WonderPeaks/__init__.py
WonderPeaks/environment.yml
WonderPeaks/user_inputs.py
WonderPeaks/NGS_user_files/NGS_user_inputs.csv
WonderPeaks/NGS_user_files/NGS_user_metadata.csv
WonderPeaks/Notebooks/PeakStream.ipynb
WonderPeaks/Notebooks/WP4ChIP.ipynb
WonderPeaks/PeakStream/AT_stretches.py
WonderPeaks/PeakStream/Helper_Functions.py
WonderPeaks/PeakStream/PeakFlags.py
WonderPeaks/PeakStream/PeakLinks.py
WonderPeaks/PeakStream/Peakstream.py
WonderPeaks/PeakStream/WonderPeaks4UTRs.py
WonderPeaks/PeakStream/__init__.py
WonderPeaks/PeakStream/feature_counts.py
WonderPeaks/PeakStream/__pycache__/AT_stretches.cpython-37.pyc
WonderPeaks/PeakStream/__pycache__/Helper_Functions.cpython-37.pyc
WonderPeaks/PeakStream/__pycache__/Links.cpython-37.pyc
WonderPeaks/PeakStream/__pycache__/PeakCollapse.cpython-37.pyc
WonderPeaks/PeakStream/__pycache__/PeakFlags.cpython-37.pyc
WonderPeaks/PeakStream/__pycache__/PeakLinks.cpython-37.pyc
WonderPeaks/PeakStream/__pycache__/Peakstream.cpython-37.pyc
WonderPeaks/PeakStream/__pycache__/WonderPeaks4UTRs.cpython-37.pyc
WonderPeaks/PeakStream/__pycache__/Wonder_Peaks_for_UTRs.cpython-37.pyc
WonderPeaks/PeakStream/__pycache__/__init__.cpython-37.pyc
WonderPeaks/PeakStream/__pycache__/feature_counts.cpython-37.pyc
WonderPeaks/WonderPeaks/FilterPeaks.py
WonderPeaks/WonderPeaks/WonderPeaks4ChIP.py
WonderPeaks/WonderPeaks/__init__.py
WonderPeaks/WonderPeaks/metadata_functions.py
WonderPeaks/WonderPeaks/__pycache__/FilterPeaks.cpython-37.pyc
WonderPeaks/WonderPeaks/__pycache__/WonderPeaks4ChIP.cpython-37.pyc
WonderPeaks/WonderPeaks/__pycache__/__init__.cpython-37.pyc
WonderPeaks/WonderPeaks/__pycache__/metadata_functions.cpython-37.pyc
WonderPeaks/__pycache__/Helper_Functions.cpython-37.pyc
WonderPeaks/__pycache__/PeakStream.cpython-36.pyc
WonderPeaks/__pycache__/PeakStream.cpython-37.pyc
WonderPeaks/__pycache__/user_inputs.cpython-37.pyc
WonderPeaks-0.1.14.dist-info/METADATA
WonderPeaks-0.1.14.dist-info/WHEEL
WonderPeaks-0.1.14.dist-info/top_level.txt
WonderPeaks-0.1.14.dist-info/RECORD
