Metadata-Version: 2.2
Name: WonderPeaks
Version: 0.1.14
Summary: functions for peakcalling enriched peaks in ChIP-seq and untranslateed regions in 3'RNA-seq in Fungi
Home-page: https://github.com/mgarber21/WonderPeaks
Author: Megan E. Garber
Author-email: "Megan E. Garber" <mgarber21@gmail.com>
Maintainer-email: "Megan E. Garber" <mgarber21@gmail.com>
License: MIT
Project-URL: Repository, https://github.com/mgarber21/WonderPeaks.git
Project-URL: Bug Tracker, https://github.com/mgarber21/WonderPeaks/issues
Keywords: ChIP-seq,RNA-seq,NGS,WonderPeaks,peak calling,UTR,dynamic UTR,Fungi,Yeast
Classifier: Development Status :: 4 - Beta
Classifier: Programming Language :: Python
Requires-Python: >=3.6
Dynamic: author
Dynamic: home-page
